{
  "__requires": [
    {
      "id": "grafana",
      "name": "Grafana",
      "type": "grafana",
      "version": "10.4.0"
    },
    {
      "id": "influxdb",
      "name": "InfluxDB",
      "type": "datasource",
      "version": "2.7.0"
    },
    {
      "id": "timeseries",
      "name": "Time series",
      "type": "panel",
      "version": ""
    },
    {
      "id": "stat",
      "name": "Stat",
      "type": "panel",
      "version": ""
    },
    {
      "id": "table",
      "name": "Table",
      "type": "panel",
      "version": ""
    },
    {
      "id": "piechart",
      "name": "Pie chart",
      "type": "panel",
      "version": ""
    }
  ],
  "annotations": {
    "list": [
      {
        "builtIn": 1,
        "datasource": {
          "type": "grafana",
          "uid": "-- Grafana --"
        },
        "enable": true,
        "hide": true,
        "iconColor": "rgba(0, 211, 255, 1)",
        "name": "Annotations & Alerts",
        "target": {
          "limit": 100,
          "matchAny": false,
          "tags": [],
          "type": "dashboard"
        },
        "type": "dashboard"
      }
    ]
  },
  "editable": true,
  "fiscalYearStartMonth": 0,
  "graphTooltip": 0,
  "links": [],
  "liveNow": false,
  "panels": [
    {
      "datasource": {
        "type": "influxdb",
        "uid": "InfluxDB"
      },
      "fieldConfig": {
        "defaults": {
          "color": {
            "mode": "thresholds"
          },
          "thresholds": {
            "mode": "absolute",
            "steps": [
              {
                "color": "green",
                "value": null
              },
              {
                "color": "red",
                "value": 1
              }
            ]
          },
          "unit": "none"
        },
        "overrides": []
      },
      "gridPos": {
        "h": 4,
        "w": 6,
        "x": 0,
        "y": 0
      },
      "id": 1,
      "options": {
        "colorMode": "background",
        "graphMode": "none",
        "justifyMode": "center",
        "orientation": "auto",
        "reduceOptions": {
          "calcs": [
            "lastNotNull"
          ],
          "fields": "",
          "values": false
        },
        "textMode": "value"
      },
      "targets": [
        {
          "datasource": {
            "type": "influxdb",
            "uid": "InfluxDB"
          },
          "query": "from(bucket: \"telemetry\")\n  |> range(start: v.timeRangeStart, stop: v.timeRangeStop)\n  |> filter(fn: (r) => r._measurement == \"telemetry\")\n  |> filter(fn: (r) => r._field == \"value\")\n  |> aggregateWindow(every: 1m, fn: count, createEmpty: false)\n  |> last()",
          "refId": "A"
        }
      ],
      "title": "Telemetry ingest (points/min)",
      "type": "stat"
    },
    {
      "datasource": {
        "type": "influxdb",
        "uid": "InfluxDB"
      },
      "fieldConfig": {
        "defaults": {
          "color": {
            "mode": "thresholds"
          },
          "thresholds": {
            "mode": "absolute",
            "steps": [
              {
                "color": "green",
                "value": null
              },
              {
                "color": "red",
                "value": 1
              }
            ]
          },
          "unit": "none"
        },
        "overrides": []
      },
      "gridPos": {
        "h": 4,
        "w": 6,
        "x": 6,
        "y": 0
      },
      "id": 2,
      "options": {
        "colorMode": "background",
        "graphMode": "none",
        "justifyMode": "center",
        "orientation": "auto",
        "reduceOptions": {
          "calcs": [
            "lastNotNull"
          ],
          "fields": "",
          "values": false
        },
        "textMode": "value"
      },
      "targets": [
        {
          "datasource": {
            "type": "influxdb",
            "uid": "InfluxDB"
          },
          "query": "from(bucket: \"telemetry\")\n  |> range(start: v.timeRangeStart, stop: v.timeRangeStop)\n  |> filter(fn: (r) => r._measurement == \"alerts\")\n  |> filter(fn: (r) => r.status == \"active\")\n  |> filter(fn: (r) => r._field == \"value\")\n  |> aggregateWindow(every: 1m, fn: count, createEmpty: false)\n  |> last()",
          "refId": "A"
        }
      ],
      "title": "Active alerts (events/min)",
      "type": "stat"
    },
    {
      "datasource": {
        "type": "influxdb",
        "uid": "InfluxDB"
      },
      "fieldConfig": {
        "defaults": {
          "color": {
            "mode": "thresholds"
          },
          "thresholds": {
            "mode": "absolute",
            "steps": [
              {
                "color": "green",
                "value": null
              },
              {
                "color": "orange",
                "value": 3
              },
              {
                "color": "red",
                "value": 8
              }
            ]
          },
          "unit": "none"
        },
        "overrides": []
      },
      "gridPos": {
        "h": 4,
        "w": 6,
        "x": 12,
        "y": 0
      },
      "id": 3,
      "options": {
        "colorMode": "background",
        "graphMode": "none",
        "justifyMode": "center",
        "orientation": "auto",
        "reduceOptions": {
          "calcs": [
            "lastNotNull"
          ],
          "fields": "",
          "values": false
        },
        "textMode": "value"
      },
      "targets": [
        {
          "datasource": {
            "type": "influxdb",
            "uid": "InfluxDB"
          },
          "query": "from(bucket: \"telemetry\")\n  |> range(start: v.timeRangeStart, stop: v.timeRangeStop)\n  |> filter(fn: (r) => r._measurement == \"telemetry\")\n  |> filter(fn: (r) => r._field == \"value\")\n  |> group()\n  |> unique(column: \"device_id\")\n  |> count(column: \"_value\")",
          "refId": "A"
        }
      ],
      "title": "Devices seen in window",
      "type": "stat"
    },
    {
      "datasource": {
        "type": "influxdb",
        "uid": "InfluxDB"
      },
      "fieldConfig": {
        "defaults": {
          "color": {
            "mode": "continuous-GrYlRd"
          },
          "unit": "none"
        },
        "overrides": []
      },
      "gridPos": {
        "h": 4,
        "w": 6,
        "x": 18,
        "y": 0
      },
      "id": 4,
      "options": {
        "displayLabels": [
          "name",
          "percent"
        ],
        "legend": {
          "displayMode": "list",
          "placement": "right",
          "showLegend": true
        },
        "pieType": "pie",
        "reduceOptions": {
          "calcs": [
            "lastNotNull"
          ],
          "fields": "",
          "values": true
        },
        "tooltip": {
          "mode": "single"
        }
      },
      "targets": [
        {
          "datasource": {
            "type": "influxdb",
            "uid": "InfluxDB"
          },
          "query": "from(bucket: \"telemetry\")\n  |> range(start: v.timeRangeStart, stop: v.timeRangeStop)\n  |> filter(fn: (r) => r._measurement == \"telemetry\")\n  |> filter(fn: (r) => r.metric == \"door_open\")\n  |> filter(fn: (r) => r._field == \"value\")\n  |> map(fn: (r) => ({ r with state: if r._value >= 0.5 then \"open\" else \"closed\" }))\n  |> group(columns: [\"state\"])\n  |> count()\n  |> keep(columns: [\"state\", \"_value\"])",
          "refId": "A"
        }
      ],
      "title": "Door-open state distribution",
      "type": "piechart"
    },
    {
      "datasource": {
        "type": "influxdb",
        "uid": "InfluxDB"
      },
      "fieldConfig": {
        "defaults": {
          "color": {
            "mode": "palette-classic"
          },
          "unit": "celsius"
        },
        "overrides": []
      },
      "gridPos": {
        "h": 8,
        "w": 12,
        "x": 0,
        "y": 4
      },
      "id": 5,
      "options": {
        "legend": {
          "calcs": [],
          "displayMode": "list",
          "placement": "bottom",
          "showLegend": true
        },
        "tooltip": {
          "mode": "multi",
          "sort": "none"
        }
      },
      "targets": [
        {
          "datasource": {
            "type": "influxdb",
            "uid": "InfluxDB"
          },
          "query": "from(bucket: \"telemetry\")\n  |> range(start: v.timeRangeStart, stop: v.timeRangeStop)\n  |> filter(fn: (r) => r._measurement == \"telemetry\")\n  |> filter(fn: (r) => r.metric == \"temperature\")\n  |> filter(fn: (r) => r._field == \"value\")\n  |> aggregateWindow(every: v.windowPeriod, fn: mean, createEmpty: false)",
          "refId": "A"
        }
      ],
      "title": "Temperature by device",
      "type": "timeseries"
    },
    {
      "datasource": {
        "type": "influxdb",
        "uid": "InfluxDB"
      },
      "fieldConfig": {
        "defaults": {
          "color": {
            "mode": "palette-classic"
          },
          "unit": "percent"
        },
        "overrides": []
      },
      "gridPos": {
        "h": 8,
        "w": 12,
        "x": 12,
        "y": 4
      },
      "id": 6,
      "options": {
        "legend": {
          "calcs": [],
          "displayMode": "list",
          "placement": "bottom",
          "showLegend": true
        },
        "tooltip": {
          "mode": "multi",
          "sort": "none"
        }
      },
      "targets": [
        {
          "datasource": {
            "type": "influxdb",
            "uid": "InfluxDB"
          },
          "query": "from(bucket: \"telemetry\")\n  |> range(start: v.timeRangeStart, stop: v.timeRangeStop)\n  |> filter(fn: (r) => r._measurement == \"telemetry\")\n  |> filter(fn: (r) => r.metric == \"humidity\" or r.metric == \"battery\")\n  |> filter(fn: (r) => r._field == \"value\")\n  |> aggregateWindow(every: v.windowPeriod, fn: mean, createEmpty: false)",
          "refId": "A"
        }
      ],
      "title": "Humidity and battery trends",
      "type": "timeseries"
    },
    {
      "datasource": {
        "type": "influxdb",
        "uid": "InfluxDB"
      },
      "fieldConfig": {
        "defaults": {
          "color": {
            "mode": "palette-classic"
          },
          "unit": "dBm"
        },
        "overrides": []
      },
      "gridPos": {
        "h": 8,
        "w": 12,
        "x": 0,
        "y": 12
      },
      "id": 7,
      "options": {
        "legend": {
          "calcs": [],
          "displayMode": "list",
          "placement": "bottom",
          "showLegend": true
        },
        "tooltip": {
          "mode": "multi",
          "sort": "none"
        }
      },
      "targets": [
        {
          "datasource": {
            "type": "influxdb",
            "uid": "InfluxDB"
          },
          "query": "from(bucket: \"telemetry\")\n  |> range(start: v.timeRangeStart, stop: v.timeRangeStop)\n  |> filter(fn: (r) => r._measurement == \"telemetry\")\n  |> filter(fn: (r) => r.metric == \"signal_strength\")\n  |> filter(fn: (r) => r._field == \"value\")\n  |> aggregateWindow(every: v.windowPeriod, fn: mean, createEmpty: false)",
          "refId": "A"
        }
      ],
      "title": "Signal strength (offline pulse visibility)",
      "type": "timeseries"
    },
    {
      "datasource": {
        "type": "influxdb",
        "uid": "InfluxDB"
      },
      "fieldConfig": {
        "defaults": {
          "color": {
            "mode": "palette-classic"
          },
          "unit": "celsius"
        },
        "overrides": []
      },
      "gridPos": {
        "h": 8,
        "w": 12,
        "x": 12,
        "y": 12
      },
      "id": 8,
      "options": {
        "legend": {
          "calcs": [],
          "displayMode": "list",
          "placement": "bottom",
          "showLegend": true
        },
        "tooltip": {
          "mode": "multi",
          "sort": "none"
        }
      },
      "targets": [
        {
          "datasource": {
            "type": "influxdb",
            "uid": "InfluxDB"
          },
          "query": "vals =\nfrom(bucket: \"telemetry\")\n  |> range(start: v.timeRangeStart, stop: v.timeRangeStop)\n  |> filter(fn: (r) => r._measurement == \"alerts\")\n  |> filter(fn: (r) => r.status == \"active\")\n  |> filter(fn: (r) => r._field == \"value\")\n  |> aggregateWindow(every: v.windowPeriod, fn: last, createEmpty: false)\n\nths =\nfrom(bucket: \"telemetry\")\n  |> range(start: v.timeRangeStart, stop: v.timeRangeStop)\n  |> filter(fn: (r) => r._measurement == \"alerts\")\n  |> filter(fn: (r) => r.status == \"active\")\n  |> filter(fn: (r) => r._field == \"threshold\")\n  |> aggregateWindow(every: v.windowPeriod, fn: last, createEmpty: false)\n\nunion(tables: [vals, ths])\n  |> pivot(rowKey: [\"_time\", \"device_id\", \"metric\"], columnKey: [\"_field\"], valueColumn: \"_value\")\n  |> map(fn: (r) => ({ r with intensity: float(v: r.value) - float(v: r.threshold) }))\n  |> keep(columns: [\"_time\", \"device_id\", \"metric\", \"intensity\"])",
          "refId": "A"
        }
      ],
      "title": "Alert intensity (value - threshold)",
      "type": "timeseries"
    },
    {
      "datasource": {
        "type": "influxdb",
        "uid": "InfluxDB"
      },
      "fieldConfig": {
        "defaults": {
          "color": {
            "mode": "thresholds"
          },
          "custom": {
            "align": "auto",
            "displayMode": "auto"
          }
        },
        "overrides": []
      },
      "gridPos": {
        "h": 8,
        "w": 12,
        "x": 0,
        "y": 20
      },
      "id": 9,
      "options": {
        "cellHeight": "sm",
        "footer": {
          "countRows": false,
          "fields": "",
          "reducer": [
            "sum"
          ],
          "show": false
        },
        "showHeader": true,
        "sortBy": [
          {
            "desc": true,
            "displayName": "_time"
          }
        ]
      },
      "targets": [
        {
          "datasource": {
            "type": "influxdb",
            "uid": "InfluxDB"
          },
          "query": "from(bucket: \"telemetry\")\n  |> range(start: -30m)\n  |> filter(fn: (r) => r._measurement == \"alerts\")\n  |> filter(fn: (r) => r.status == \"active\")\n  |> filter(fn: (r) => r._field == \"value\" or r._field == \"threshold\" or r._field == \"consecutive_breach_count\" or r._field == \"message\")\n  |> pivot(rowKey: [\"_time\", \"device_id\", \"metric\"], columnKey: [\"_field\"], valueColumn: \"_value\")\n  |> sort(columns: [\"_time\"], desc: true)\n  |> limit(n: 50)",
          "refId": "A"
        }
      ],
      "title": "Recent active alerts (last 50)",
      "type": "table"
    },
    {
      "datasource": {
        "type": "influxdb",
        "uid": "InfluxDB"
      },
      "fieldConfig": {
        "defaults": {
          "color": {
            "mode": "thresholds"
          },
          "custom": {
            "align": "auto",
            "displayMode": "auto"
          }
        },
        "overrides": []
      },
      "gridPos": {
        "h": 8,
        "w": 12,
        "x": 12,
        "y": 20
      },
      "id": 10,
      "options": {
        "cellHeight": "sm",
        "footer": {
          "countRows": false,
          "fields": "",
          "reducer": [
            "sum"
          ],
          "show": false
        },
        "showHeader": true
      },
      "targets": [
        {
          "datasource": {
            "type": "influxdb",
            "uid": "InfluxDB"
          },
          "query": "from(bucket: \"telemetry\")\n  |> range(start: -10m)\n  |> filter(fn: (r) => r._measurement == \"telemetry\")\n  |> filter(fn: (r) => r.metric == \"temperature\" or r.metric == \"humidity\" or r.metric == \"battery\" or r.metric == \"signal_strength\" or r.metric == \"open_duration_seconds\")\n  |> filter(fn: (r) => r._field == \"value\")\n  |> group(columns: [\"device_id\", \"metric\"])\n  |> last()\n  |> pivot(rowKey: [\"device_id\"], columnKey: [\"metric\"], valueColumn: \"_value\")\n  |> sort(columns: [\"device_id\"])",
          "refId": "A"
        }
      ],
      "title": "Latest metrics by device",
      "type": "table"
    }
  ],
  "refresh": "5s",
  "schemaVersion": 39,
  "style": "dark",
  "tags": [
    "oncovax",
    "prompt-f",
    "observability"
  ],
  "templating": {
    "list": []
  },
  "time": {
    "from": "now-30m",
    "to": "now"
  },
  "timepicker": {
    "refresh_intervals": [
      "5s",
      "10s",
      "30s",
      "1m",
      "5m"
    ]
  },
  "timezone": "utc",
  "title": "OncoVax Observability \u2013 Prompt F Final",
  "uid": "oncovax-obsv-f-v1",
  "weekStart": ""
}